GoogleScholarReport/__init__.py
GoogleScholarReport/collector.py
GoogleScholarReport-0.1.7.data/scripts/collector
test/__init__.py
test/test_gsr.py
GoogleScholarReport-0.1.7.dist-info/LICENSE
GoogleScholarReport-0.1.7.dist-info/METADATA
GoogleScholarReport-0.1.7.dist-info/WHEEL
GoogleScholarReport-0.1.7.dist-info/top_level.txt
GoogleScholarReport-0.1.7.dist-info/RECORD
