Metadata-Version: 2.1
Name: GoogleScholarReport
Version: 0.1.7
Summary: Bibliographic capture system for non-scrapping data sources
Home-page: https://github.com/readingwritingcode/google-scholar-report
Author: Colav
Author-email: grupocolav@udea.edu.co
License: BSD
Platform: UNKNOWN
Classifier: Development Status :: 3 - Alpha
Classifier: Intended Audience :: Developers
Classifier: Topic :: Software Development :: Build Tools
Classifier: License :: OSI Approved :: MIT License
Classifier: Programming Language :: Python :: 3
Classifier: Programming Language :: Python :: 3.6
Classifier: Programming Language :: Python :: 3.7
Classifier: Programming Language :: Python :: 3.8
Classifier: Programming Language :: Python :: 3.9
Requires-Dist: beautifulsoup4
Requires-Dist: bibtexparser
Requires-Dist: bs4
Requires-Dist: et-xmlfile
Requires-Dist: future
Requires-Dist: fuzzywuzzy
Requires-Dist: helium
Requires-Dist: lxml
Requires-Dist: numpy
Requires-Dist: openpyxl
Requires-Dist: pandas
Requires-Dist: pyparsing
Requires-Dist: python-dateutil
Requires-Dist: python-Levenshtein
Requires-Dist: pytz
Requires-Dist: selenium
Requires-Dist: six
Requires-Dist: soupsieve
Requires-Dist: Unidecode
Requires-Dist: urllib3
